AUTHORS
LICENSE
MANIFEST.in
README.rst
setup.py
django_simple_spam_blocker.egg-info/PKG-INFO
django_simple_spam_blocker.egg-info/SOURCES.txt
django_simple_spam_blocker.egg-info/dependency_links.txt
django_simple_spam_blocker.egg-info/not-zip-safe
django_simple_spam_blocker.egg-info/top_level.txt
simplespamblocker/__init__.py
simplespamblocker/admin.py
simplespamblocker/fields.py
simplespamblocker/forms.py
simplespamblocker/middleware.py
simplespamblocker/models.py
simplespamblocker/settings.py
simplespamblocker/migrations/0001_initial.py
simplespamblocker/migrations/__init__.py
simplespamblocker/tests/__init__.py
simplespamblocker/tests/middleware.py
simplespamblocker/tests/urls.py
simplespamblocker/tests/templates/simplespamblocker/blocked.html