Metadata-Version: 1.0
Name: django-simple-spam-blocker
Version: 0.1.0
Summary: Simple spam blocker for Django
Home-page: http://github.com/moqada/django-simple-spam-blocker/
Author: Masahiko Okada
Author-email: moqada@gmail.com
License: BSD License
Keywords: django,spam
Platform: UNKNOWN
Classifier: Development Status :: 3 - Alpha
Classifier: Environment :: Plugins
Classifier: Framework :: Django
Classifier: Intended Audience :: Developers
Classifier: License :: OSI Approved :: BSD License
Classifier: Programming Language :: Python
Classifier: Topic :: Software Development :: Libraries :: Python Modules
